algorithm4t/__init__.py
algorithm4t/common.py
algorithm4t/poker_sort.py
algorithm4t/search_guess.py
algorithm4t/images/back.png
algorithm4t/images/bulb.png
algorithm4t/images/check.png
algorithm4t/images/club1.png
algorithm4t/images/club10.png
algorithm4t/images/club11.png
algorithm4t/images/club12.png
algorithm4t/images/club13.png
algorithm4t/images/club2.png
algorithm4t/images/club3.png
algorithm4t/images/club4.png
algorithm4t/images/club5.png
algorithm4t/images/club6.png
algorithm4t/images/club7.png
algorithm4t/images/club8.png
algorithm4t/images/club9.png
algorithm4t/images/diamond1.png
algorithm4t/images/diamond10.png
algorithm4t/images/diamond11.png
algorithm4t/images/diamond12.png
algorithm4t/images/diamond13.png
algorithm4t/images/diamond2.png
algorithm4t/images/diamond3.png
algorithm4t/images/diamond4.png
algorithm4t/images/diamond5.png
algorithm4t/images/diamond6.png
algorithm4t/images/diamond7.png
algorithm4t/images/diamond8.png
algorithm4t/images/diamond9.png
algorithm4t/images/heart1.png
algorithm4t/images/heart10.png
algorithm4t/images/heart11.png
algorithm4t/images/heart12.png
algorithm4t/images/heart13.png
algorithm4t/images/heart2.png
algorithm4t/images/heart3.png
algorithm4t/images/heart4.png
algorithm4t/images/heart5.png
algorithm4t/images/heart6.png
algorithm4t/images/heart7.png
algorithm4t/images/heart8.png
algorithm4t/images/heart9.png
algorithm4t/images/low_rocket.png
algorithm4t/images/poker_sort_bg.png
algorithm4t/images/poker_sort_logo.png
algorithm4t/images/ruler.png
algorithm4t/images/search_arrow.png
algorithm4t/images/search_guess_bg.png
algorithm4t/images/search_guess_logo.png
algorithm4t/images/spade1.png
algorithm4t/images/spade10.png
algorithm4t/images/spade11.png
algorithm4t/images/spade12.png
algorithm4t/images/spade13.png
algorithm4t/images/spade2.png
algorithm4t/images/spade3.png
algorithm4t/images/spade4.png
algorithm4t/images/spade5.png
algorithm4t/images/spade6.png
algorithm4t/images/spade7.png
algorithm4t/images/spade8.png
algorithm4t-0.0.1.dist-info/LICENSE
algorithm4t-0.0.1.dist-info/METADATA
algorithm4t-0.0.1.dist-info/WHEEL
algorithm4t-0.0.1.dist-info/top_level.txt
algorithm4t-0.0.1.dist-info/RECORD
